jera/__about__.py
jera/__init__.py
jera-0.0.0a0.dist-info/LICENSE
jera-0.0.0a0.dist-info/METADATA
jera-0.0.0a0.dist-info/WHEEL
jera-0.0.0a0.dist-info/RECORD
