Metadata-Version: 2.1
Name: jera
Version: 0.0.0a0
Summary: ...
Home-page: https://github.com/INSPXRXD/jera
License: MIT
Keywords: Domain Driven Design
Author: INSPXRXD
Author-email: inspxrxd@gmail.com
Requires-Python: >=3.8,<4.0
Classifier: License :: OSI Approved :: MIT License
Classifier: Programming Language :: Python :: 3
Classifier: Programming Language :: Python :: 3.8
Classifier: Programming Language :: Python :: 3.9
Classifier: Programming Language :: Python :: 3.10
Classifier: Programming Language :: Python :: 3.11
Classifier: Programming Language :: Python :: 3.12
Project-URL: Bug Tracker, https://github.com/INSPXRXD/jera/issues
Project-URL: Documentation, https://github.com/INSPXRXD/jera
Project-URL: Repository, https://github.com/INSPXRXD/jera
